concretefhe_hnumpy-0.0.10-py3.9-nspkg.pth
concretefhe/hnumpy/__init__.py
concretefhe/hnumpy/file.py
concretefhe_hnumpy-0.0.10.dist-info/LICENSE
concretefhe_hnumpy-0.0.10.dist-info/METADATA
concretefhe_hnumpy-0.0.10.dist-info/WHEEL
concretefhe_hnumpy-0.0.10.dist-info/namespace_packages.txt
concretefhe_hnumpy-0.0.10.dist-info/top_level.txt
concretefhe_hnumpy-0.0.10.dist-info/RECORD
